debug.py
id2xml.py
id2xml/__init__.py
id2xml/__init__.pyc
id2xml/confparser.py
id2xml/id2xml.1.gz
id2xml/parser.py
id2xml/data/v2.rnc
id2xml/data/v2.rng
id2xml/data/v3.rnc
id2xml/data/v3.rng
id2xml-0.9.2.data/data/share/man/man1/id2xml.1.gz
id2xml-0.9.2.dist-info/DESCRIPTION.rst
id2xml-0.9.2.dist-info/METADATA
id2xml-0.9.2.dist-info/RECORD
id2xml-0.9.2.dist-info/WHEEL
id2xml-0.9.2.dist-info/entry_points.txt
id2xml-0.9.2.dist-info/metadata.json
id2xml-0.9.2.dist-info/top_level.txt
