Metadata-Version: 2.0
Name: id2xml
Version: 0.9.2
Summary: Convert text format RFCs and Internet-Drafts to .xml format
Home-page: https://tools.ietf.org/tools/ietfdb/browser/branch/elft/id2rfcx/
Author: Henrik Levkowetz
Author-email: henrik@levkowetz.com
License: Simplified BSD
Keywords: Internet-Draft text to xml conversion
Platform: UNKNOWN
Classifier: Development Status :: 4 - Beta
Classifier: Intended Audience :: Other Audience
Classifier: Topic :: Text Processing
Classifier: Topic :: Text Processing :: Markup :: XML
Classifier: License :: OSI Approved :: BSD License
Classifier: Programming Language :: Python :: 2
Classifier: Programming Language :: Python :: 2.7
Requires-Dist: lxml
Requires-Dist: pathlib
Requires-Dist: pyterminalsize
Requires-Dist: six
Requires-Dist: xml2rfc
Provides-Extra: dev
Requires-Dist: twine; extra == 'dev'
